rkt_lib_toolkit/__init__.py
rkt_lib_toolkit/rkt_ai_lib/AI.py
rkt_lib_toolkit/rkt_ai_lib/__init__.py
rkt_lib_toolkit/rkt_ai_lib/Artificial_Neuron/Neuronal_Network.py
rkt_lib_toolkit/rkt_ai_lib/Artificial_Neuron/Perceptron.py
rkt_lib_toolkit/rkt_ai_lib/Artificial_Neuron/__init__.py
rkt_lib_toolkit/rkt_ai_lib/Artificial_Neuron/Layers/Layers.py
rkt_lib_toolkit/rkt_ai_lib/Artificial_Neuron/Layers/__init__.py
rkt_lib_toolkit/rkt_config_lib/Config.py
rkt_lib_toolkit/rkt_config_lib/__init__.py
rkt_lib_toolkit/rkt_exception_lib/DBException.py
rkt_lib_toolkit/rkt_exception_lib/LoggerException.py
rkt_lib_toolkit/rkt_exception_lib/__init__.py
rkt_lib_toolkit/rkt_logger_lib/Logger.py
rkt_lib_toolkit/rkt_logger_lib/__init__.py
rkt_lib_toolkit/rkt_logger_lib/Filters/MyFilters.py
rkt_lib_toolkit/rkt_logger_lib/Filters/__init__.py
rkt_lib_toolkit/rkt_tool_lib/Tool.py
rkt_lib_toolkit/rkt_tool_lib/__init__.py
tests/__init__.py
tests/test_AI.py
tests/test_Config.py
tests/test_Logger.py
tests/test_Tool.py
rkt_lib_toolkit-1.8.0.dist-info/LICENSE
rkt_lib_toolkit-1.8.0.dist-info/METADATA
rkt_lib_toolkit-1.8.0.dist-info/WHEEL
rkt_lib_toolkit-1.8.0.dist-info/top_level.txt
rkt_lib_toolkit-1.8.0.dist-info/RECORD
